main.py
rug_check_mcp-0.1.0.dist-info/licenses/LICENSE
rug_check_mcp-0.1.0.dist-info/METADATA
rug_check_mcp-0.1.0.dist-info/WHEEL
rug_check_mcp-0.1.0.dist-info/top_level.txt
rug_check_mcp-0.1.0.dist-info/RECORD
