Metadata-Version: 2.4
Name: rug-check-mcp
Version: 0.1.0
Summary: An MCP server that detects potential rug pull risks in Solana meme tokens.
Requires-Python: >=3.13
License-File: LICENSE
Requires-Dist: dotenv>=0.9.9
Requires-Dist: mcp[cli]>=1.5.0
Requires-Dist: requests>=2.32.3
Dynamic: license-file
